[{"date": "09-Apr-2026", "symbol": "GMBREW", "company": "GM Breweries Limited"}, {"date": "09-Apr-2026", "symbol": "TCS", "company": "Tata Consultancy Services Limited"}, {"date": "18-Apr-2026", "symbol": "ICICIBANK", "company": "ICICI Bank Limited"}, {"date": "23-Apr-2026", "symbol": "INFY", "company": "Infosys Limited"}, {"date": "23-Apr-2026", "symbol": "TATACAP", "company": "Tata Capital Limited"}, {"date": "23-Apr-2026", "symbol": "UTIAMC", "company": "UTI Asset Management Company Limited"}, {"date": "25-Apr-2026", "symbol": "INDIACEM", "company": "The India Cements Limited"}, {"date": "27-Apr-2026", "symbol": "ULTRACEMCO", "company": "UltraTech Cement Limited"}, {"date": "06-May-2026", "symbol": "KANSAINER", "company": "Kansai Nerolac Paints Limited"}, {"date": "07-May-2026", "symbol": "DABUR", "company": "Dabur India Limited"}, {"date": "22-May-2026", "symbol": "HINDALCO", "company": "Hindalco Industries Limited"}, {"date": "22-May-2026", "symbol": "TTKPRESTIG", "company": "TTK Prestige Limited"}]